chronokit/__init__.py
chronokit/arima/__base_model.py
chronokit/arima/__init__.py
chronokit/arima/__initialization.py
chronokit/arima/_sarima.py
chronokit/base/__init__.py
chronokit/base/_initializers.py
chronokit/base/_models.py
chronokit/decomposition/__init__.py
chronokit/decomposition/_classical_decomposition.py
chronokit/decomposition/_mstl.py
chronokit/decomposition/_stl.py
chronokit/exponential_smoothing/__base_model.py
chronokit/exponential_smoothing/__init__.py
chronokit/exponential_smoothing/__initialization.py
chronokit/exponential_smoothing/_ets.py
chronokit/exponential_smoothing/_smoothing.py
chronokit/networks/__init__.py
chronokit/networks/_generator.py
chronokit/networks/_narx.py
chronokit/preprocessing/__init__.py
chronokit/preprocessing/_dataloader.py
chronokit/preprocessing/autocorrelations.py
chronokit/preprocessing/data_transforms.py
chronokit/utils/__init__.py
chronokit/utils/evaluation/__init__.py
chronokit/utils/evaluation/_model_evaluation.py
chronokit/utils/evaluation/metrics.py
chronokit/utils/vis_utils/__init__.py
chronokit/utils/vis_utils/data_plots.py
chronokit/utils/vis_utils/model_plots.py
chrono_kit-1.2.2.dist-info/LICENSE
chrono_kit-1.2.2.dist-info/METADATA
chrono_kit-1.2.2.dist-info/WHEEL
chrono_kit-1.2.2.dist-info/RECORD
